app-come-before/__init__.py
app-come-before/server/__init__.py
app-come-before/server/app.py
logic/__init__.py
logic/graph.py
server/__init__.py
server/app.py
app_come_before-0.1.5.dist-info/METADATA
app_come_before-0.1.5.dist-info/WHEEL
app_come_before-0.1.5.dist-info/entry_points.txt
app_come_before-0.1.5.dist-info/top_level.txt
app_come_before-0.1.5.dist-info/RECORD
