Metadata-Version: 2.1
Name: app-come-before
Version: 0.1.5
Summary: UNKNOWN
Home-page: UNKNOWN
License: UNKNOWN
Platform: UNKNOWN
Requires-Dist: flask
Requires-Dist: pygraphviz
Requires-Dist: pytest
